argscalculator/__init__.py
argscalculator/index.py
argscalculator-0.0.1.dist-info/METADATA
argscalculator-0.0.1.dist-info/WHEEL
argscalculator-0.0.1.dist-info/entry_points.txt
argscalculator-0.0.1.dist-info/top_level.txt
argscalculator-0.0.1.dist-info/RECORD
