Metadata-Version: 2.1
Name: argscalculator
Version: 0.0.1
Summary: Django project initialize
Author: Salman Latif
Author-email: salu33956@gmail.com
Classifier: Programming Language :: Python :: 3
Classifier: License :: OSI Approved :: MIT License
Classifier: Operating System :: OS Independent
Requires-Python: >=3.6
Requires-Dist: Django >=3.8
Requires-Dist: virtualenv >=20
